corsheaders/__init__.py
corsheaders/apps.py
corsheaders/checks.py
corsheaders/conf.py
corsheaders/defaults.py
corsheaders/middleware.py
corsheaders/py.typed
corsheaders/signals.py
django_cors_headers-4.6.0.dist-info/LICENSE
django_cors_headers-4.6.0.dist-info/METADATA
django_cors_headers-4.6.0.dist-info/WHEEL
django_cors_headers-4.6.0.dist-info/top_level.txt
django_cors_headers-4.6.0.dist-info/RECORD
