Metadata-Version: 2.1
Name: django-cors-headers
Version: 4.6.0
Summary: django-cors-headers is a Django application for handling the server headers required for Cross-Origin Resource Sharing (CORS).
Author-email: Otto Yiu <otto@live.ca>
Maintainer-email: Adam Johnson <me@adamj.eu>
Project-URL: Changelog, https://github.com/adamchainz/django-cors-headers/blob/main/CHANGELOG.rst
Project-URL: Funding, https://adamj.eu/books/
Project-URL: Repository, https://github.com/adamchainz/django-cors-headers
Keywords: api,cors,django,middleware,rest
Classifier: Development Status :: 5 - Production/Stable
Classifier: Environment :: Web Environment
Classifier: Framework :: Django
Classifier: Framework :: Django :: 4.2
Classifier: Framework :: Django :: 5.0
Classifier: Framework :: Django :: 5.1
Classifier: Intended Audience :: Developers
Classifier: License :: OSI Approved :: MIT License
Classifier: Natural Language :: English
Classifier: Operating System :: OS Independent
Classifier: Programming Language :: Python :: 3 :: Only
Classifier: Programming Language :: Python :: 3.9
Classifier: Programming Language :: Python :: 3.10
Classifier: Programming Language :: Python :: 3.11
Classifier: Programming Language :: Python :: 3.12
Classifier: Programming Language :: Python :: 3.13
Classifier: Programming Language :: Python :: Implementation :: CPython
Classifier: Typing :: Typed
Requires-Python: >=3.9
License-File: LICENSE
Requires-Dist: asgiref>=3.6
Requires-Dist: django>=4.2
